setup.py
torch_checker/__init__.py
torch_checker/check.py
torch_checker.egg-info/PKG-INFO
torch_checker.egg-info/SOURCES.txt
torch_checker.egg-info/dependency_links.txt
torch_checker.egg-info/requires.txt
torch_checker.egg-info/top_level.txt